Metadata-Version: 2.1
Name: pypkgtest
Version: 0.0.1
Summary: PyPI Test
Home-page: https://github.com/
Author: iRuxu
Author-email: rx6@qq.com
License: UNKNOWN
Platform: UNKNOWN
Classifier: Programming Language :: Python :: 3
Classifier: License :: OSI Approved :: MIT License
Classifier: Operating System :: OS Independent
